gcslock/__init__.py
gcslock/__version__.py
gcslock/_cli.py
gcslock/_logger.py
gcslock/_ttl_dict.py
gcslock/core.py
gcslock/exception.py
gcslock/_apis/__init__.py
gcslock/_apis/accessor.py
gcslock/_apis/model.py
gcslock-0.0.6.dist-info/METADATA
gcslock-0.0.6.dist-info/WHEEL
gcslock-0.0.6.dist-info/entry_points.txt
gcslock-0.0.6.dist-info/licenses/LICENSE
gcslock-0.0.6.dist-info/RECORD
