Metadata-Version: 2.4
Name: gcslock
Version: 0.0.6
Summary: Add your description here
Author-email: minthem <114272528+minthem@users.noreply.github.com>
License-File: LICENSE
Requires-Python: >=3.10
Requires-Dist: google-auth>=2
Requires-Dist: requests>=2
